llmstudio_proxy/__init__.py
llmstudio_proxy/cli.py
llmstudio_proxy/config.py
llmstudio_proxy/provider.py
llmstudio_proxy/server.py
llmstudio_proxy/utils.py
llmstudio_proxy-1.0.6.dist-info/METADATA
llmstudio_proxy-1.0.6.dist-info/WHEEL
llmstudio_proxy-1.0.6.dist-info/entry_points.txt
llmstudio_proxy-1.0.6.dist-info/RECORD
