Metadata-Version: 2.1
Name: llmstudio-proxy
Version: 1.0.6
Summary: LLMstudio Proxy is the module of LLMstudio that allows calling any LLM as a Service Provider in proxy server. By leveraging LLMstudio Proxy, you can have a centralized point for connecting to any provider running independently from your application.
Author: Claudio Lemos
Author-email: claudio.lemos@tensorops.ai
Requires-Python: >=3.9,<4.0
Classifier: Programming Language :: Python :: 3
Classifier: Programming Language :: Python :: 3.9
Classifier: Programming Language :: Python :: 3.10
Classifier: Programming Language :: Python :: 3.11
Classifier: Programming Language :: Python :: 3.12
Classifier: Programming Language :: Python :: 3.13
Requires-Dist: fastapi (>=0.115.5,<0.116.0)
Requires-Dist: llmstudio-core (>=1.0.0,<2.0.0)
Requires-Dist: pydantic (>=2.5,<3.0)
Requires-Dist: python-dotenv (>=0.4.0,<2.0.0)
Requires-Dist: requests (>=2.31,<3.0)
Requires-Dist: tiktoken (>=0.7,<0.8)
Requires-Dist: toml (>=0.10,<0.11)
Requires-Dist: uvicorn (>=0.27,<0.28)
